spark_jdbc_profiler/__init__.py
spark_jdbc_profiler/__main__.py
spark_jdbc_profiler/base.py
spark_jdbc_profiler/cli.py
spark_jdbc_profiler/segmentation_profiler/__init__.py
spark_jdbc_profiler/segmentation_profiler/segmentation_gen.py
spark_jdbc_profiler/whole_db_profiler/__init__.py
spark_jdbc_profiler/whole_db_profiler/mysql_db_profiler.py
spark_jdbc_profiler/whole_db_profiler/sqlserver_db_profiler.py
spark_jdbc_profiler-1.0.4.dist-info/LICENSE
spark_jdbc_profiler-1.0.4.dist-info/METADATA
spark_jdbc_profiler-1.0.4.dist-info/WHEEL
spark_jdbc_profiler-1.0.4.dist-info/entry_points.txt
spark_jdbc_profiler-1.0.4.dist-info/top_level.txt
spark_jdbc_profiler-1.0.4.dist-info/RECORD
