Metadata-Version: 2.1
Name: spark-jdbc-profiler
Version: 1.0.4
Summary: Awesome spark_jdbc_profiler created by hgbink
Home-page: https://github.com/hgbink/spark-jdbc-profiler/
Author: hgbink
License: UNKNOWN
Platform: UNKNOWN
License-File: LICENSE
Provides-Extra: test
Requires-Dist: pytest ; extra == 'test'
Requires-Dist: coverage ; extra == 'test'
Requires-Dist: flake8 ; extra == 'test'
Requires-Dist: black ; extra == 'test'
Requires-Dist: isort ; extra == 'test'
Requires-Dist: pytest-cov ; extra == 'test'
Requires-Dist: codecov ; extra == 'test'
Requires-Dist: mypy ; extra == 'test'
Requires-Dist: gitchangelog ; extra == 'test'
Requires-Dist: mkdocs ; extra == 'test'
